impscope/__init__.py
impscope/__main__.py
impscope/cli.py
impscope/core.py
impscope/formatter.py
impscope-0.1.0.dist-info/licenses/LICENSE
impscope-0.1.0.dist-info/METADATA
impscope-0.1.0.dist-info/WHEEL
impscope-0.1.0.dist-info/entry_points.txt
impscope-0.1.0.dist-info/top_level.txt
impscope-0.1.0.dist-info/RECORD
