Metadata-Version: 2.4
Name: impscope
Version: 0.1.0
Summary: Python Dependency Impact Analyzer
Author-email: zh-he <zh.he@siat.ac.cn>
License: MIT License
Project-URL: Homepage, https://github.com/zh-he/impscope
Project-URL: Repository, https://github.com/zh-he/impscope
Project-URL: Issues, https://github.com/zh-he/impscope/issues
Keywords: python,dependencies,analysis,impact
Classifier: Development Status :: 3 - Alpha
Classifier: Intended Audience :: Developers
Classifier: License :: OSI Approved :: MIT License
Classifier: Operating System :: OS Independent
Classifier: Programming Language :: Python :: 3
Classifier: Programming Language :: Python :: 3.7
Classifier: Programming Language :: Python :: 3.8
Classifier: Programming Language :: Python :: 3.9
Classifier: Programming Language :: Python :: 3.10
Classifier: Programming Language :: Python :: 3.11
Requires-Python: >=3.7
License-File: LICENSE
Dynamic: license-file
